lrz_sync_share/__init__.py
lrz_sync_share/lrz_session.py
lrz_sync_share-0.1.0.dist-info/DESCRIPTION.rst
lrz_sync_share-0.1.0.dist-info/METADATA
lrz_sync_share-0.1.0.dist-info/RECORD
lrz_sync_share-0.1.0.dist-info/WHEEL
lrz_sync_share-0.1.0.dist-info/metadata.json
lrz_sync_share-0.1.0.dist-info/top_level.txt
