Metadata-Version: 2.0
Name: lrz-sync-share
Version: 0.1.0
Summary: LRZ Sync+Share library for uploads and other file management
Home-page: https://github.com/instance01/lrz-sync-share-lib
Author: Instance01
Author-email: use.github.issues@instancedev.com
License: MIT
Platform: UNKNOWN
Classifier: Development Status :: 3 - Alpha
Classifier: License :: OSI Approved :: MIT License
Classifier: Programming Language :: Python :: 3
Classifier: Topic :: Utilities
Requires-Dist: requests
